neuronica/__init__.py
neuronica/loss.py
neuronica/model.py
neuronica/layers/__init__.py
neuronica/layers/activations.py
neuronica/layers/layer.py
neuronica/utils/__init__.py
neuronica/utils/backend.py
neuronica/utils/serialization.py
neuronica-0.0.1.dist-info/METADATA
neuronica-0.0.1.dist-info/WHEEL
neuronica-0.0.1.dist-info/top_level.txt
neuronica-0.0.1.dist-info/RECORD
