Metadata-Version: 2.1
Name: neuronica
Version: 0.0.1
Summary: A simple deep learning library
Author: Kyle Bolo
Author-email: <bkyle9023@gmail.com>
Keywords: ai,deep learning,neural networks
Classifier: Development Status :: 1 - Planning
Classifier: Intended Audience :: Developers
Classifier: Programming Language :: Python :: 3
Classifier: Operating System :: Unix
Classifier: Operating System :: MacOS :: MacOS X
Classifier: Operating System :: Microsoft :: Windows
Requires-Dist: numpy
Requires-Dist: scipy
